sparkaid/__init__.py
sparkaid/__main__.py
sparkaid-1.0.0.dist-info/LICENSE
sparkaid-1.0.0.dist-info/METADATA
sparkaid-1.0.0.dist-info/WHEEL
sparkaid-1.0.0.dist-info/top_level.txt
sparkaid-1.0.0.dist-info/RECORD
