Metadata-Version: 2.1
Name: sparkaid
Version: 1.0.0
Summary: Utils for working with Spark
Author-email: Averell Levan <lvhuyen@yahoo.com>
Project-URL: Homepage, https://github.com/lvhuyen/SparkAid
Keywords: SPARK,DATAFRAME,MANIPULATE
Classifier: Development Status :: 4 - Beta
Classifier: Intended Audience :: Developers
Classifier: Topic :: Software Development :: Build Tools
Classifier: License :: OSI Approved :: GNU Lesser General Public License v3 or later (LGPLv3+)
Classifier: Programming Language :: Python :: 3
Requires-Python: >=3.4
License-File: LICENSE
Requires-Dist: pyspark (>=2.4.0)
Provides-Extra: dev
Requires-Dist: pip-tools ; extra == 'dev'
Requires-Dist: pytest ; extra == 'dev'
